odoo9_addon_website_crm_privacy_policy-9.0.1.0.0.99.dev3-py2.7-nspkg.pth
odoo9_addon_website_crm_privacy_policy-9.0.1.0.0.99.dev3.dist-info/DESCRIPTION.rst
odoo9_addon_website_crm_privacy_policy-9.0.1.0.0.99.dev3.dist-info/METADATA
odoo9_addon_website_crm_privacy_policy-9.0.1.0.0.99.dev3.dist-info/RECORD
odoo9_addon_website_crm_privacy_policy-9.0.1.0.0.99.dev3.dist-info/WHEEL
odoo9_addon_website_crm_privacy_policy-9.0.1.0.0.99.dev3.dist-info/metadata.json
odoo9_addon_website_crm_privacy_policy-9.0.1.0.0.99.dev3.dist-info/namespace_packages.txt
odoo9_addon_website_crm_privacy_policy-9.0.1.0.0.99.dev3.dist-info/top_level.txt
odoo_addons/website_crm_privacy_policy/README.rst
odoo_addons/website_crm_privacy_policy/__init__.py
odoo_addons/website_crm_privacy_policy/__openerp__.py
odoo_addons/website_crm_privacy_policy/i18n/ca.po
odoo_addons/website_crm_privacy_policy/i18n/de.po
odoo_addons/website_crm_privacy_policy/i18n/el_GR.po
odoo_addons/website_crm_privacy_policy/i18n/es.po
odoo_addons/website_crm_privacy_policy/i18n/fr.po
odoo_addons/website_crm_privacy_policy/i18n/it.po
odoo_addons/website_crm_privacy_policy/i18n/pt_BR.po
odoo_addons/website_crm_privacy_policy/i18n/ru.po
odoo_addons/website_crm_privacy_policy/i18n/sl.po
odoo_addons/website_crm_privacy_policy/i18n/website_crm_privacy_policy.pot
odoo_addons/website_crm_privacy_policy/static/description/icon.png
odoo_addons/website_crm_privacy_policy/templates/contactus.xml
